{
  "@context": "https://schema.org",
  "@type": "Dataset",
  "@id": "http://localhost:3000/materials/wood/hardwood/cherry-laser-cleaning#dataset",
  "name": "Cherry Laser Cleaning Dataset",
  "description": "Comprehensive laser cleaning parameters and material properties for Cherry. Includes thermal, optical, mechanical, and laser interaction properties validated against industry standards.",
  "version": "1.0",
  "dateModified": "2025-11-06",
  "datePublished": "2025-11-06",
  "license": {
    "@type": "CreativeWork",
    "name": "Creative Commons Attribution 4.0 International",
    "url": "https://creativecommons.org/licenses/by/4.0/",
    "description": "Free to share and adapt with attribution"
  },
  "creator": {
    "@type": "Organization",
    "name": "Z-Beam Laser Cleaning Research Lab",
    "url": "https://www.z-beam.com",
    "contactPoint": {
      "@type": "ContactPoint",
      "contactType": "Data Support",
      "email": "info@z-beam.com"
    }
  },
  "publisher": {
    "@type": "Organization",
    "name": "Z-Beam Laser Cleaning Research Lab",
    "url": "https://www.z-beam.com"
  },
  "keywords": [
    "cherry",
    "laser cleaning",
    "wood",
    "hardwood",
    "laser cleaning",
    "material properties",
    "industrial cleaning",
    "surface preparation",
    "laser parameters",
    "material characterization",
    "thermal properties",
    "optical properties"
  ],
  "inLanguage": "en-US",
  "temporalCoverage": "2020/2025",
  "spatialCoverage": "Global",
  "measurementTechnique": "Laser ablation testing, material characterization, spectroscopy",
  "includedInDataCatalog": {
    "@type": "DataCatalog",
    "name": "Z-Beam Material Properties Database",
    "description": "Comprehensive laser cleaning parameters and material properties for industrial applications",
    "url": "https://www.z-beam.com/datasets"
  },
  "distribution": [
    {
      "@type": "DataDownload",
      "encodingFormat": "application/json",
      "contentUrl": "http://localhost:3000/datasets/materials/cherry-laser-cleaning.json",
      "name": "Cherry Dataset (JSON)"
    },
    {
      "@type": "DataDownload",
      "encodingFormat": "text/csv",
      "contentUrl": "http://localhost:3000/datasets/materials/cherry-laser-cleaning.csv",
      "name": "Cherry Dataset (CSV)"
    },
    {
      "@type": "DataDownload",
      "encodingFormat": "text/plain",
      "contentUrl": "http://localhost:3000/datasets/materials/cherry-laser-cleaning.txt",
      "name": "Cherry Dataset (TXT)"
    }
  ],
  "isAccessibleForFree": true,
  "usageInfo": "http://localhost:3000/datasets/usage-terms",
  "dataQuality": {
    "verificationMethod": "Multi-source cross-reference with industry standards",
    "sources": [
      "ASM Handbook",
      "Peer-reviewed literature",
      "AI-verified research"
    ],
    "updateFrequency": "Quarterly",
    "accuracyLevel": "High (±5%)",
    "lastVerified": "2025-11-06"
  },
  "material": {
    "name": "Cherry",
    "slug": "cherry-laser-cleaning",
    "classification": {
      "category": "wood",
      "subcategory": "hardwood"
    },
    "laserParameters": {},
    "materialProperties": {
      "material_characteristics": {
        "label": "Material Characteristics",
        "percentage": 40,
        "fractureToughness": {
          "value": 0.38,
          "unit": "MPa m^{1/2}",
          "source": "ai_research",
          "min": 0.33,
          "max": 4.4
        },
        "thermalDestruction": {
          "value": 275,
          "unit": "°C",
          "source": "ai_research",
          "min": 273,
          "max": 600
        },
        "density": {
          "value": 580,
          "unit": "kg/m³",
          "source": "ai_research",
          "min": 0.12,
          "max": 1.5
        },
        "oxidationResistance": {
          "value": 0.72,
          "unit": "dimensionless (relative scale 0-1, 1=excellent resistance)",
          "source": "ai_research",
          "min": 82,
          "max": 204
        },
        "laserReflectivity": {
          "value": 0.23,
          "unit": "dimensionless",
          "source": "ai_research",
          "min": 10,
          "max": 60
        },
        "thermalExpansion": {
          "value": 0.000032,
          "unit": "K^{-1}",
          "source": "ai_research",
          "min": 3,
          "max": 60
        },
        "thermalConductivity": {
          "value": 0.163,
          "unit": "W/(m·K)",
          "source": "ai_research",
          "min": 0.04,
          "max": 0.4
        },
        "youngsModulus": {
          "value": 10.27,
          "unit": "GPa",
          "source": "ai_research",
          "min": 5,
          "max": 20000
        },
        "hardness": {
          "value": 4226,
          "unit": "N",
          "source": "ai_research",
          "min": 1,
          "max": 5000
        },
        "specificHeat": {
          "value": 1380,
          "unit": "J/(kg·K)",
          "source": "ai_research",
          "min": 800,
          "max": 2500
        },
        "laserAbsorption": {
          "value": 0.93,
          "unit": "dimensionless",
          "source": "ai_research",
          "min": 1,
          "max": 50
        },
        "compressiveStrength": {
          "value": 40.3,
          "unit": "MPa",
          "source": "ai_research",
          "min": 20,
          "max": 80
        },
        "tensileStrength": {
          "value": 70.3,
          "unit": "MPa",
          "source": "ai_research",
          "min": 20,
          "max": 200
        },
        "thermalDiffusivity": {
          "value": 1.28e-7,
          "unit": "m²/s",
          "source": "ai_research",
          "min": 0.0001,
          "max": 0.4
        },
        "flexuralStrength": {
          "value": 67.8,
          "unit": "MPa",
          "source": "ai_research",
          "min": 40,
          "max": 150
        },
        "corrosionResistance": {
          "value": 0.35,
          "unit": "dimensionless (relative durability index)",
          "source": "ai_research",
          "min": 2,
          "max": 8
        },
        "porosity": {
          "value": 0.667,
          "unit": "fraction",
          "source": "ai_research",
          "min": 12,
          "max": 65
        }
      },
      "laser_material_interaction": {
        "label": "Laser-Material Interaction",
        "percentage": 40,
        "absorptivity": {
          "value": 0.85,
          "unit": "dimensionless",
          "min": 0.7,
          "max": 0.95,
          "source": "ai_research"
        },
        "absorptionCoefficient": {
          "value": 500000,
          "unit": "m⁻¹",
          "min": 10000,
          "max": 1000000,
          "source": "ai_research"
        },
        "laserDamageThreshold": {
          "value": 2.5,
          "unit": "J/cm²",
          "min": 0.5,
          "max": 10,
          "source": "ai_research"
        },
        "thermalShockResistance": {
          "value": 1.2,
          "unit": "MW/m",
          "min": 0.5,
          "max": 3,
          "source": "ai_research"
        },
        "reflectivity": {
          "value": 0.15,
          "unit": "dimensionless",
          "min": 0.05,
          "max": 0.3,
          "source": "ai_research"
        },
        "thermalDestructionPoint": {
          "value": 500,
          "unit": "K",
          "min": 450,
          "max": 600,
          "source": "ai_research"
        },
        "vaporPressure": {
          "value": 50,
          "unit": "Pa",
          "min": 1,
          "max": 1000,
          "source": "ai_research"
        }
      }
    },
    "applications": [],
    "safetyConsiderations": [],
    "faqs": []
  },
  "variableMeasured": [
    {
      "@type": "PropertyValue",
      "propertyID": "fractureToughness",
      "name": "Fracture Toughness",
      "description": "Fracture Toughness - material characteristics",
      "value": 0.38,
      "unitText": "MPa m^{1/2}",
      "minValue": 0.33,
      "maxValue": 4.4,
      "measurementTechnique": "ai_research"
    },
    {
      "@type": "PropertyValue",
      "propertyID": "thermalDestruction",
      "name": "Thermal Destruction",
      "description": "Thermal Destruction - material characteristics",
      "value": 275,
      "unitText": "°C",
      "minValue": 273,
      "maxValue": 600,
      "measurementTechnique": "ai_research"
    },
    {
      "@type": "PropertyValue",
      "propertyID": "density",
      "name": "Density",
      "description": "Density - material characteristics",
      "value": 580,
      "unitText": "kg/m³",
      "minValue": 0.12,
      "maxValue": 1.5,
      "measurementTechnique": "ai_research"
    },
    {
      "@type": "PropertyValue",
      "propertyID": "oxidationResistance",
      "name": "Oxidation Resistance",
      "description": "Oxidation Resistance - material characteristics",
      "value": 0.72,
      "unitText": "dimensionless (relative scale 0-1, 1=excellent resistance)",
      "minValue": 82,
      "maxValue": 204,
      "measurementTechnique": "ai_research"
    },
    {
      "@type": "PropertyValue",
      "propertyID": "laserReflectivity",
      "name": "Laser Reflectivity",
      "description": "Laser Reflectivity - material characteristics",
      "value": 0.23,
      "unitText": "dimensionless",
      "minValue": 10,
      "maxValue": 60,
      "measurementTechnique": "ai_research"
    },
    {
      "@type": "PropertyValue",
      "propertyID": "thermalExpansion",
      "name": "Thermal Expansion",
      "description": "Thermal Expansion - material characteristics",
      "value": 0.000032,
      "unitText": "K^{-1}",
      "minValue": 3,
      "maxValue": 60,
      "measurementTechnique": "ai_research"
    },
    {
      "@type": "PropertyValue",
      "propertyID": "thermalConductivity",
      "name": "Thermal Conductivity",
      "description": "Thermal Conductivity - material characteristics",
      "value": 0.163,
      "unitText": "W/(m·K)",
      "minValue": 0.04,
      "maxValue": 0.4,
      "measurementTechnique": "ai_research"
    },
    {
      "@type": "PropertyValue",
      "propertyID": "youngsModulus",
      "name": "Youngs Modulus",
      "description": "Youngs Modulus - material characteristics",
      "value": 10.27,
      "unitText": "GPa",
      "minValue": 5,
      "maxValue": 20000,
      "measurementTechnique": "ai_research"
    },
    {
      "@type": "PropertyValue",
      "propertyID": "hardness",
      "name": "Hardness",
      "description": "Hardness - material characteristics",
      "value": 4226,
      "unitText": "N",
      "minValue": 1,
      "maxValue": 5000,
      "measurementTechnique": "ai_research"
    },
    {
      "@type": "PropertyValue",
      "propertyID": "specificHeat",
      "name": "Specific Heat",
      "description": "Specific Heat - material characteristics",
      "value": 1380,
      "unitText": "J/(kg·K)",
      "minValue": 800,
      "maxValue": 2500,
      "measurementTechnique": "ai_research"
    },
    {
      "@type": "PropertyValue",
      "propertyID": "laserAbsorption",
      "name": "Laser Absorption",
      "description": "Laser Absorption - material characteristics",
      "value": 0.93,
      "unitText": "dimensionless",
      "minValue": 1,
      "maxValue": 50,
      "measurementTechnique": "ai_research"
    },
    {
      "@type": "PropertyValue",
      "propertyID": "compressiveStrength",
      "name": "Compressive Strength",
      "description": "Compressive Strength - material characteristics",
      "value": 40.3,
      "unitText": "MPa",
      "minValue": 20,
      "maxValue": 80,
      "measurementTechnique": "ai_research"
    },
    {
      "@type": "PropertyValue",
      "propertyID": "tensileStrength",
      "name": "Tensile Strength",
      "description": "Tensile Strength - material characteristics",
      "value": 70.3,
      "unitText": "MPa",
      "minValue": 20,
      "maxValue": 200,
      "measurementTechnique": "ai_research"
    },
    {
      "@type": "PropertyValue",
      "propertyID": "thermalDiffusivity",
      "name": "Thermal Diffusivity",
      "description": "Thermal Diffusivity - material characteristics",
      "value": 1.28e-7,
      "unitText": "m²/s",
      "minValue": 0.0001,
      "maxValue": 0.4,
      "measurementTechnique": "ai_research"
    },
    {
      "@type": "PropertyValue",
      "propertyID": "flexuralStrength",
      "name": "Flexural Strength",
      "description": "Flexural Strength - material characteristics",
      "value": 67.8,
      "unitText": "MPa",
      "minValue": 40,
      "maxValue": 150,
      "measurementTechnique": "ai_research"
    },
    {
      "@type": "PropertyValue",
      "propertyID": "corrosionResistance",
      "name": "Corrosion Resistance",
      "description": "Corrosion Resistance - material characteristics",
      "value": 0.35,
      "unitText": "dimensionless (relative durability index)",
      "minValue": 2,
      "maxValue": 8,
      "measurementTechnique": "ai_research"
    },
    {
      "@type": "PropertyValue",
      "propertyID": "porosity",
      "name": "Porosity",
      "description": "Porosity - material characteristics",
      "value": 0.667,
      "unitText": "fraction",
      "minValue": 12,
      "maxValue": 65,
      "measurementTechnique": "ai_research"
    },
    {
      "@type": "PropertyValue",
      "propertyID": "absorptivity",
      "name": "Absorptivity",
      "description": "Absorptivity - laser material interaction",
      "value": 0.85,
      "unitText": "dimensionless",
      "minValue": 0.7,
      "maxValue": 0.95,
      "measurementTechnique": "ai_research"
    },
    {
      "@type": "PropertyValue",
      "propertyID": "absorptionCoefficient",
      "name": "Absorption Coefficient",
      "description": "Absorption Coefficient - laser material interaction",
      "value": 500000,
      "unitText": "m⁻¹",
      "minValue": 10000,
      "maxValue": 1000000,
      "measurementTechnique": "ai_research"
    },
    {
      "@type": "PropertyValue",
      "propertyID": "laserDamageThreshold",
      "name": "Laser Damage Threshold",
      "description": "Laser Damage Threshold - laser material interaction",
      "value": 2.5,
      "unitText": "J/cm²",
      "minValue": 0.5,
      "maxValue": 10,
      "measurementTechnique": "ai_research"
    },
    {
      "@type": "PropertyValue",
      "propertyID": "thermalShockResistance",
      "name": "Thermal Shock Resistance",
      "description": "Thermal Shock Resistance - laser material interaction",
      "value": 1.2,
      "unitText": "MW/m",
      "minValue": 0.5,
      "maxValue": 3,
      "measurementTechnique": "ai_research"
    },
    {
      "@type": "PropertyValue",
      "propertyID": "reflectivity",
      "name": "Reflectivity",
      "description": "Reflectivity - laser material interaction",
      "value": 0.15,
      "unitText": "dimensionless",
      "minValue": 0.05,
      "maxValue": 0.3,
      "measurementTechnique": "ai_research"
    },
    {
      "@type": "PropertyValue",
      "propertyID": "thermalDestructionPoint",
      "name": "Thermal Destruction Point",
      "description": "Thermal Destruction Point - laser material interaction",
      "value": 500,
      "unitText": "K",
      "minValue": 450,
      "maxValue": 600,
      "measurementTechnique": "ai_research"
    },
    {
      "@type": "PropertyValue",
      "propertyID": "vaporPressure",
      "name": "Vapor Pressure",
      "description": "Vapor Pressure - laser material interaction",
      "value": 50,
      "unitText": "Pa",
      "minValue": 1,
      "maxValue": 1000,
      "measurementTechnique": "ai_research"
    }
  ],
  "citation": "Z-Beam (2025). Cherry Laser Cleaning Dataset. Retrieved from http://localhost:3000/materials/wood/hardwood/cherry-laser-cleaning"
}