{
  "@context": "https://schema.org",
  "@type": "Dataset",
  "@id": "https://www.z-beam.com/materials/iridium#dataset",
  "name": "Iridium Laser Cleaning Dataset",
  "description": "When working with iridium in laser cleaning operations, we've found it stands out from other non-ferrous metals with its unmatched resistance to corrosion and extreme heat, ensuring reliable performance in aerospace and chemical processing without degradation—so always monitor for potential brittleness under repeated thermal cycles.",
  "version": "1.0",
  "dateModified": "2025-12-23",
  "datePublished": "2025-12-23",
  "license": {
    "@type": "CreativeWork",
    "name": "Creative Commons Attribution 4.0 International",
    "url": "https://creativecommons.org/licenses/by/4.0/"
  },
  "creator": {
    "@type": "Organization",
    "name": "Z-Beam Laser Cleaning Research Lab",
    "url": "https://www.z-beam.com"
  },
  "publisher": {
    "@type": "Organization",
    "name": "Z-Beam Laser Cleaning Research Lab",
    "url": "https://www.z-beam.com"
  },
  "keywords": [
    "Iridium",
    "laser cleaning",
    "material properties",
    "industrial cleaning",
    "surface preparation",
    "metal",
    "non-ferrous"
  ],
  "variableMeasured": [
    {
      "@type": "PropertyValue",
      "name": "Electricalconductivity",
      "description": "Material Characteristics: electricalConductivity",
      "value": "21230000.0",
      "unitText": "S/m",
      "minValue": null,
      "maxValue": null
    },
    {
      "@type": "PropertyValue",
      "name": "Electricalresistivity",
      "description": "Material Characteristics: electricalResistivity",
      "value": "4.71e-08",
      "unitText": "Ω·m",
      "minValue": null,
      "maxValue": null
    },
    {
      "@type": "PropertyValue",
      "name": "Fracturetoughness",
      "description": "Material Characteristics: fractureToughness",
      "value": "3.0",
      "unitText": "MPa√m",
      "minValue": null,
      "maxValue": null
    },
    {
      "@type": "PropertyValue",
      "name": "Surfaceroughness",
      "description": "Material Characteristics: surfaceRoughness",
      "value": "0.05",
      "unitText": "μm",
      "minValue": null,
      "maxValue": null
    },
    {
      "@type": "PropertyValue",
      "name": "Youngsmodulus",
      "description": "Material Characteristics: youngsModulus",
      "value": "528.0",
      "unitText": "GPa",
      "minValue": null,
      "maxValue": null
    },
    {
      "@type": "PropertyValue",
      "name": "Oxidationresistance",
      "description": "Material Characteristics: oxidationResistance",
      "value": "1673.0",
      "unitText": "K",
      "minValue": null,
      "maxValue": null
    },
    {
      "@type": "PropertyValue",
      "name": "Density",
      "description": "Material Characteristics: density",
      "value": "22560.0",
      "unitText": "kg/m³",
      "minValue": null,
      "maxValue": null
    },
    {
      "@type": "PropertyValue",
      "name": "Hardness",
      "description": "Material Characteristics: hardness",
      "value": "1960.0",
      "unitText": "MPa",
      "minValue": null,
      "maxValue": null
    },
    {
      "@type": "PropertyValue",
      "name": "Corrosionresistance",
      "description": "Material Characteristics: corrosionResistance",
      "value": "1.156",
      "unitText": "V",
      "minValue": null,
      "maxValue": null
    },
    {
      "@type": "PropertyValue",
      "name": "Compressivestrength",
      "description": "Material Characteristics: compressiveStrength",
      "value": "1400.0",
      "unitText": "MPa",
      "minValue": null,
      "maxValue": null
    },
    {
      "@type": "PropertyValue",
      "name": "Flexuralstrength",
      "description": "Material Characteristics: flexuralStrength",
      "value": "1050.0",
      "unitText": "MPa",
      "minValue": null,
      "maxValue": null
    },
    {
      "@type": "PropertyValue",
      "name": "Tensilestrength",
      "description": "Material Characteristics: tensileStrength",
      "value": "1170.0",
      "unitText": "MPa",
      "minValue": null,
      "maxValue": null
    },
    {
      "@type": "PropertyValue",
      "name": "Porosity",
      "description": "Material Characteristics: porosity",
      "value": "0.0",
      "unitText": "%",
      "minValue": null,
      "maxValue": null
    },
    {
      "@type": "PropertyValue",
      "name": "Absorptivity",
      "description": "Material Characteristics: absorptivity",
      "value": "0.35",
      "unitText": "dimensionless",
      "minValue": null,
      "maxValue": null
    },
    {
      "@type": "PropertyValue",
      "name": "Boilingpoint",
      "description": "Material Characteristics: boilingPoint",
      "value": "4701.0",
      "unitText": "K",
      "minValue": null,
      "maxValue": null
    },
    {
      "@type": "PropertyValue",
      "name": "Absorptioncoefficient",
      "description": "Material Characteristics: absorptionCoefficient",
      "value": "61700000.0",
      "unitText": "m^{-1}",
      "minValue": null,
      "maxValue": null
    },
    {
      "@type": "PropertyValue",
      "name": "Meltingpoint",
      "description": "Material Characteristics: meltingPoint",
      "value": "2719.0",
      "unitText": "K",
      "minValue": null,
      "maxValue": null
    },
    {
      "@type": "PropertyValue",
      "name": "Vaporpressure",
      "description": "Material Characteristics: vaporPressure",
      "value": "101325.0",
      "unitText": "Pa",
      "minValue": null,
      "maxValue": null
    },
    {
      "@type": "PropertyValue",
      "name": "Thermaldestructionpoint",
      "description": "Material Characteristics: thermalDestructionPoint",
      "value": "2719.0",
      "unitText": "K",
      "minValue": null,
      "maxValue": null
    },
    {
      "@type": "PropertyValue",
      "name": "Reflectivity",
      "description": "Material Characteristics: reflectivity",
      "value": "0.71",
      "unitText": "",
      "minValue": null,
      "maxValue": null
    },
    {
      "@type": "PropertyValue",
      "name": "Thermalshockresistance",
      "description": "Material Characteristics: thermalShockResistance",
      "value": "359.0",
      "unitText": "K",
      "minValue": null,
      "maxValue": null
    },
    {
      "@type": "PropertyValue",
      "name": "Laserdamagethreshold",
      "description": "Material Characteristics: laserDamageThreshold",
      "value": "2.8",
      "unitText": "J/cm²",
      "minValue": null,
      "maxValue": null
    },
    {
      "@type": "PropertyValue",
      "name": "Absorptioncoefficient",
      "description": "Laser-Material Interaction: absorptionCoefficient",
      "value": "47200000.0",
      "unitText": "m⁻¹",
      "minValue": null,
      "maxValue": null
    },
    {
      "@type": "PropertyValue",
      "name": "Absorptivity",
      "description": "Laser-Material Interaction: absorptivity",
      "value": "0.42",
      "unitText": "dimensionless",
      "minValue": null,
      "maxValue": null
    },
    {
      "@type": "PropertyValue",
      "name": "Laserdamagethreshold",
      "description": "Laser-Material Interaction: laserDamageThreshold",
      "value": "0.45",
      "unitText": "J/cm²",
      "minValue": null,
      "maxValue": null
    },
    {
      "@type": "PropertyValue",
      "name": "Reflectivity",
      "description": "Laser-Material Interaction: reflectivity",
      "value": "0.965",
      "unitText": "dimensionless (reflectance ratio)",
      "minValue": null,
      "maxValue": null
    },
    {
      "@type": "PropertyValue",
      "name": "Thermaldestructionpoint",
      "description": "Laser-Material Interaction: thermalDestructionPoint",
      "value": "2716.0",
      "unitText": "K",
      "minValue": null,
      "maxValue": null
    },
    {
      "@type": "PropertyValue",
      "name": "Thermalshockresistance",
      "description": "Laser-Material Interaction: thermalShockResistance",
      "value": "1.8",
      "unitText": "MPa·m^0.5",
      "minValue": null,
      "maxValue": null
    },
    {
      "@type": "PropertyValue",
      "name": "Vaporpressure",
      "description": "Laser-Material Interaction: vaporPressure",
      "value": "0.0001333",
      "unitText": "Pa",
      "minValue": null,
      "maxValue": null
    },
    {
      "@type": "PropertyValue",
      "name": "Thermaldestruction",
      "description": "Laser-Material Interaction: thermalDestruction",
      "value": "2719.0",
      "unitText": "K",
      "minValue": null,
      "maxValue": null
    },
    {
      "@type": "PropertyValue",
      "name": "Specificheat",
      "description": "Laser-Material Interaction: specificHeat",
      "value": "132.0",
      "unitText": "J/kg·K",
      "minValue": null,
      "maxValue": null
    },
    {
      "@type": "PropertyValue",
      "name": "Laserreflectivity",
      "description": "Laser-Material Interaction: laserReflectivity",
      "value": "0.67",
      "unitText": "dimensionless",
      "minValue": null,
      "maxValue": null
    },
    {
      "@type": "PropertyValue",
      "name": "Thermalconductivity",
      "description": "Laser-Material Interaction: thermalConductivity",
      "value": "147.0",
      "unitText": "W/m·K",
      "minValue": null,
      "maxValue": null
    },
    {
      "@type": "PropertyValue",
      "name": "Thermalexpansion",
      "description": "Laser-Material Interaction: thermalExpansion",
      "value": "6.8",
      "unitText": "×10^{-6} K^{-1}",
      "minValue": null,
      "maxValue": null
    },
    {
      "@type": "PropertyValue",
      "name": "Laserabsorption",
      "description": "Laser-Material Interaction: laserAbsorption",
      "value": "0.12",
      "unitText": "dimensionless",
      "minValue": null,
      "maxValue": null
    },
    {
      "@type": "PropertyValue",
      "name": "Thermaldiffusivity",
      "description": "Laser-Material Interaction: thermalDiffusivity",
      "value": "4.98e-05",
      "unitText": "m²/s",
      "minValue": null,
      "maxValue": null
    },
    {
      "@type": "PropertyValue",
      "name": "Ablationthreshold",
      "description": "Laser-Material Interaction: ablationThreshold",
      "value": "2.3",
      "unitText": "J/cm²",
      "minValue": null,
      "maxValue": null
    }
  ],
  "distribution": [
    {
      "@type": "DataDownload",
      "encodingFormat": "application/json",
      "contentUrl": "https://www.z-beam.com/datasets/materials/iridium.json"
    },
    {
      "@type": "DataDownload",
      "encodingFormat": "text/csv",
      "contentUrl": "https://www.z-beam.com/datasets/materials/iridium.csv"
    },
    {
      "@type": "DataDownload",
      "encodingFormat": "text/plain",
      "contentUrl": "https://www.z-beam.com/datasets/materials/iridium.txt"
    }
  ]
}