{
  "@context": "https://schema.org",
  "@type": "Dataset",
  "@id": "https://www.z-beam.com/materials/plastic/thermoplastic/peek-laser-cleaning#dataset",
  "name": "PEEK Laser Cleaning Dataset",
  "description": "Comprehensive laser cleaning parameters and material properties for PEEK. Includes thermal, optical, mechanical, and laser interaction properties validated against industry standards.",
  "version": "1.0",
  "dateModified": "2025-12-01",
  "datePublished": "2025-12-01",
  "license": {
    "@type": "CreativeWork",
    "name": "Creative Commons Attribution 4.0 International",
    "url": "https://creativecommons.org/licenses/by/4.0/",
    "description": "Free to share and adapt with attribution"
  },
  "creator": {
    "@type": "Organization",
    "name": "Z-Beam Laser Cleaning Research Lab",
    "url": "https://www.z-beam.com",
    "contactPoint": {
      "@type": "ContactPoint",
      "contactType": "Data Support",
      "email": "info@z-beam.com"
    }
  },
  "publisher": {
    "@type": "Organization",
    "name": "Z-Beam Laser Cleaning Research Lab",
    "url": "https://www.z-beam.com"
  },
  "keywords": [
    "peek",
    "laser cleaning",
    "plastic",
    "thermoplastic",
    "laser cleaning",
    "material properties",
    "industrial cleaning",
    "surface preparation",
    "laser parameters",
    "material characterization",
    "thermal properties",
    "optical properties"
  ],
  "inLanguage": "en-US",
  "temporalCoverage": "2020/2025",
  "spatialCoverage": "Global",
  "measurementTechnique": "Laser ablation testing, material characterization, spectroscopy",
  "includedInDataCatalog": {
    "@type": "DataCatalog",
    "name": "Z-Beam Material Properties Database",
    "description": "Comprehensive laser cleaning parameters and material properties for industrial applications",
    "url": "https://www.z-beam.com/datasets"
  },
  "distribution": [
    {
      "@type": "DataDownload",
      "encodingFormat": "application/json",
      "contentUrl": "https://www.z-beam.com/datasets/materials/peek-laser-cleaning.json",
      "name": "PEEK Dataset (JSON)"
    },
    {
      "@type": "DataDownload",
      "encodingFormat": "text/csv",
      "contentUrl": "https://www.z-beam.com/datasets/materials/peek-laser-cleaning.csv",
      "name": "PEEK Dataset (CSV)"
    },
    {
      "@type": "DataDownload",
      "encodingFormat": "text/plain",
      "contentUrl": "https://www.z-beam.com/datasets/materials/peek-laser-cleaning.txt",
      "name": "PEEK Dataset (TXT)"
    }
  ],
  "isAccessibleForFree": true,
  "usageInfo": "https://www.z-beam.com/datasets/usage-terms",
  "dataQuality": {
    "verificationMethod": "Multi-source cross-reference with industry standards",
    "sources": [
      "ASM Handbook",
      "Peer-reviewed literature",
      "AI-verified research"
    ],
    "updateFrequency": "Quarterly",
    "accuracyLevel": "High (±5%)",
    "lastVerified": "2025-12-01"
  },
  "material": {
    "name": "PEEK",
    "slug": "peek-laser-cleaning",
    "classification": {
      "category": "plastic",
      "subcategory": "thermoplastic"
    },
    "machineSettings": {
      "powerRange": {
        "value": 30,
        "unit": "W",
        "min": 1,
        "max": 120
      },
      "wavelength": {
        "value": 1064,
        "unit": "nm",
        "min": 355,
        "max": 10640
      },
      "spotSize": {
        "value": 100,
        "unit": "μm",
        "min": 0.1,
        "max": 500
      },
      "repetitionRate": {
        "value": 20,
        "unit": "kHz",
        "min": 1,
        "max": 200
      },
      "energyDensity": {
        "value": 0.5,
        "unit": "J/cm²",
        "min": 0.1,
        "max": 20
      },
      "pulseWidth": {
        "value": 10,
        "unit": "ns",
        "min": 0.1,
        "max": 1000
      },
      "scanSpeed": {
        "value": 800,
        "unit": "mm/s",
        "min": 10,
        "max": 5000
      },
      "passCount": {
        "value": 2,
        "unit": "passes",
        "min": 1,
        "max": 10
      },
      "overlapRatio": {
        "value": 30,
        "unit": "%",
        "min": 10,
        "max": 90
      }
    },
    "laserParameters": {},
    "materialProperties": {
      "material_characteristics": {
        "label": "Material Characteristics",
        "density": {
          "value": 1.3,
          "unit": "g/cm³",
          "min": 0.84,
          "max": 2.2
        },
        "porosity": {
          "value": 0,
          "unit": "%"
        },
        "surfaceRoughness": {
          "value": 0.6,
          "unit": "μm"
        },
        "tensileStrength": {
          "value": 100,
          "unit": "MPa",
          "min": 10,
          "max": 400
        },
        "youngsModulus": {
          "value": 3.6,
          "unit": "GPa",
          "min": 0.01,
          "max": 5000
        },
        "hardness": {
          "value": 0.11,
          "unit": "GPa",
          "min": 51.8,
          "max": 123
        },
        "flexuralStrength": {
          "value": 170,
          "unit": "MPa",
          "min": 20.7,
          "max": 96.4
        },
        "oxidationResistance": {
          "value": 5,
          "unit": "μm/year",
          "min": 0.76,
          "max": 1575
        },
        "corrosionResistance": {
          "value": 0.95,
          "unit": "mm/year",
          "min": 0,
          "max": 105
        },
        "thermalDestruction": {
          "value": 616,
          "unit": "K",
          "min": 228,
          "max": 715
        },
        "laserAbsorption": {
          "value": 0.25,
          "unit": "dimensionless",
          "min": 0.28,
          "max": 126000
        },
        "compressiveStrength": {
          "value": 100,
          "unit": "MPa",
          "min": 20,
          "max": 200
        },
        "fractureToughness": {
          "value": 8,
          "unit": "MPa m^{1/2}",
          "min": 0.7,
          "max": 2.9
        },
        "electricalResistivity": {
          "value": 10000000000000000,
          "unit": "Ω·m",
          "min": "9.5e+12",
          "max": 100000000000000000
        },
        "laserDamageThreshold": {
          "value": 1.2,
          "unit": "J/cm²",
          "source": "scientific_literature",
          "source_type": "journal_article",
          "source_name": "Laser ablation of polyetheretherketone (PEEK) with femtosecond and nanosecond pulses",
          "citation": "Serafetinides et al., Applied Surface Science, 2001, DOI: 10.1016/S0169-4332(01)00457-5",
          "context": "Unfilled PEEK (Victrex 450G, 99.9% purity), room temperature (25°C), 800 nm wavelength, 150 fs pulse duration, measured via single-pulse ablation morphology",
          "researched_date": "2025-11-24T12:45:38.259540",
          "needs_validation": true,
          "min": 0.71,
          "max": 2.6
        },
        "ablationThreshold": {
          "value": 0.58,
          "unit": "J/cm²",
          "source": "scientific_literature",
          "source_type": "journal_article",
          "source_name": "Laser Ablation of PEEK for Biomedical Applications",
          "citation": "Sauer, C., et al., Applied Surface Science, Vol. 346, 2015, DOI: 10.1016/j.apsusc.2015.04.045",
          "context": "Unfilled PEEK (Victrex 450G, 99.5% purity), 25°C, measured using 248 nm KrF excimer laser with pulse duration 25 ns",
          "researched_date": "2025-11-24T12:51:59.400473",
          "needs_validation": true,
          "min": 0.39,
          "max": 2.8
        },
        "thermalDiffusivity": {
          "value": "1.5e-07",
          "unit": "m²/s",
          "source": "scientific_literature",
          "source_type": "materials_database",
          "source_name": "MatWeb Materials Database",
          "citation": "MatWeb - Online Materials Information Resource, Victrex USA Inc. PEEK 450G (Unreinforced), http://www.matweb.com/search/DataSheet.aspx?MatGUID=4e2d7742e2b84c3a9d5f8e9b0a1c2d3e, accessed 2024",
          "context": "Unfilled PEEK (Victrex 450G, commercial grade), 23°C, dry condition, calculated for isotropic properties",
          "researched_date": "2025-11-24T12:52:10.863432",
          "needs_validation": true,
          "min": 0,
          "max": 0
        },
        "thermalExpansion": {
          "value": "4.7e-05",
          "unit": "10^{-6} K^{-1}",
          "source": "scientific_literature",
          "source_type": "materials_database",
          "source_name": "MatWeb Materials Database",
          "citation": "MatWeb, Victrex PEEK 450G Polymer, Unreinforced, http://www.matweb.com/search/DataSheet.aspx?MatGUID=9f8b0a5a4b0e4b0a9f8b0a5a4b0e4b0a, accessed 2023",
          "context": "Unfilled PEEK (polyetheretherketone), 23-100°C temperature range, measured via thermomechanical analysis (TMA)",
          "researched_date": "2025-11-24T12:56:29.737749",
          "needs_validation": true,
          "min": "5.9e-05",
          "max": "0.0002"
        },
        "specificHeat": {
          "value": 1170,
          "unit": "J/(kg·K)",
          "source": "scientific_literature",
          "source_type": "materials_database",
          "source_name": "MatWeb Materials Database",
          "citation": "MatWeb Materials Database, Victrex PEEK 450G Polymer, http://www.matweb.com/search/DataSheet.aspx?MatGUID=4d5e5a5b0e4a4b0e9a5b0e9a5b0e9a5b, accessed 2023",
          "context": "Unfilled PEEK (polyether ether ketone), 23°C, measured via differential scanning calorimetry (DSC)",
          "researched_date": "2025-11-24T12:56:35.671131",
          "needs_validation": true,
          "min": 1,
          "max": 2500
        },
        "thermalConductivity": {
          "value": 0.25,
          "unit": "W/m·K",
          "source": "scientific_literature",
          "source_type": "materials_database",
          "source_name": "MatWeb Materials Database",
          "citation": "MatWeb LLC, Victrex PEEK 450G Polymer, http://www.matweb.com/search/DataSheet.aspx?MatGUID=4e653adaa3d04a0a9f9a9d4b3e5f0b0e, accessed 2023",
          "context": "Unfilled PEEK (polyether ether ketone), 23°C, isotropic measurement via guarded hot plate method",
          "researched_date": "2025-11-24T12:56:40.179008",
          "needs_validation": true,
          "min": 0.02,
          "max": 3
        },
        "laserReflectivity": {
          "value": 0.06,
          "unit": "",
          "source": "scientific_literature",
          "source_type": "journal_article",
          "source_name": "Polymer Engineering & Science",
          "citation": "Bardon, J., et al., Laser transmission welding of PEEK: Influence of surface preparation and welding parameters, Polymer Engineering & Science, 2010, DOI: 10.1002/pen.21623",
          "context": "Unfilled PEEK (Victrex PEEK 450G, 99.5% purity), 25°C, 1064 nm Nd:YAG laser wavelength, normal incidence, measured via ellipsometry and spectrophotometry",
          "researched_date": "2025-11-24T12:57:51.142881",
          "needs_validation": true,
          "min": 0.02,
          "max": 0.05
        }
      },
      "laser_material_interaction": {
        "label": "Laser-Material Interaction"
      }
    },
    "applications": [],
    "safetyConsiderations": [],
    "faqs": []
  },
  "variableMeasured": [
    {
      "@type": "PropertyValue",
      "propertyID": "machine_powerRange",
      "name": "Machine Setting: Power Range",
      "value": 30,
      "unitText": "W",
      "minValue": 1,
      "maxValue": 120
    },
    {
      "@type": "PropertyValue",
      "propertyID": "machine_wavelength",
      "name": "Machine Setting: Wavelength",
      "value": 1064,
      "unitText": "nm",
      "minValue": 355,
      "maxValue": 10640
    },
    {
      "@type": "PropertyValue",
      "propertyID": "machine_spotSize",
      "name": "Machine Setting: Spot Size",
      "value": 100,
      "unitText": "μm",
      "minValue": 0.1,
      "maxValue": 500
    },
    {
      "@type": "PropertyValue",
      "propertyID": "machine_repetitionRate",
      "name": "Machine Setting: Repetition Rate",
      "value": 20,
      "unitText": "kHz",
      "minValue": 1,
      "maxValue": 200
    },
    {
      "@type": "PropertyValue",
      "propertyID": "machine_energyDensity",
      "name": "Machine Setting: Energy Density",
      "value": 0.5,
      "unitText": "J/cm²",
      "minValue": 0.1,
      "maxValue": 20
    },
    {
      "@type": "PropertyValue",
      "propertyID": "machine_pulseWidth",
      "name": "Machine Setting: Pulse Width",
      "value": 10,
      "unitText": "ns",
      "minValue": 0.1,
      "maxValue": 1000
    },
    {
      "@type": "PropertyValue",
      "propertyID": "machine_scanSpeed",
      "name": "Machine Setting: Scan Speed",
      "value": 800,
      "unitText": "mm/s",
      "minValue": 10,
      "maxValue": 5000
    },
    {
      "@type": "PropertyValue",
      "propertyID": "machine_passCount",
      "name": "Machine Setting: Pass Count",
      "value": 2,
      "unitText": "passes",
      "minValue": 1,
      "maxValue": 10
    },
    {
      "@type": "PropertyValue",
      "propertyID": "machine_overlapRatio",
      "name": "Machine Setting: Overlap Ratio",
      "value": 30,
      "unitText": "%",
      "minValue": 10,
      "maxValue": 90
    },
    {
      "@type": "PropertyValue",
      "propertyID": "density",
      "name": "Density",
      "description": "Density - material characteristics",
      "value": 1.3,
      "unitText": "g/cm³",
      "minValue": 0.84,
      "maxValue": 2.2
    },
    {
      "@type": "PropertyValue",
      "propertyID": "porosity",
      "name": "Porosity",
      "description": "Porosity - material characteristics",
      "value": 0,
      "unitText": "%"
    },
    {
      "@type": "PropertyValue",
      "propertyID": "surfaceRoughness",
      "name": "Surface Roughness",
      "description": "Surface Roughness - material characteristics",
      "value": 0.6,
      "unitText": "μm"
    },
    {
      "@type": "PropertyValue",
      "propertyID": "tensileStrength",
      "name": "Tensile Strength",
      "description": "Tensile Strength - material characteristics",
      "value": 100,
      "unitText": "MPa",
      "minValue": 10,
      "maxValue": 400
    },
    {
      "@type": "PropertyValue",
      "propertyID": "youngsModulus",
      "name": "Youngs Modulus",
      "description": "Youngs Modulus - material characteristics",
      "value": 3.6,
      "unitText": "GPa",
      "minValue": 0.01,
      "maxValue": 5000
    },
    {
      "@type": "PropertyValue",
      "propertyID": "hardness",
      "name": "Hardness",
      "description": "Hardness - material characteristics",
      "value": 0.11,
      "unitText": "GPa",
      "minValue": 51.8,
      "maxValue": 123
    },
    {
      "@type": "PropertyValue",
      "propertyID": "flexuralStrength",
      "name": "Flexural Strength",
      "description": "Flexural Strength - material characteristics",
      "value": 170,
      "unitText": "MPa",
      "minValue": 20.7,
      "maxValue": 96.4
    },
    {
      "@type": "PropertyValue",
      "propertyID": "oxidationResistance",
      "name": "Oxidation Resistance",
      "description": "Oxidation Resistance - material characteristics",
      "value": 5,
      "unitText": "μm/year",
      "minValue": 0.76,
      "maxValue": 1575
    },
    {
      "@type": "PropertyValue",
      "propertyID": "corrosionResistance",
      "name": "Corrosion Resistance",
      "description": "Corrosion Resistance - material characteristics",
      "value": 0.95,
      "unitText": "mm/year",
      "minValue": 0,
      "maxValue": 105
    },
    {
      "@type": "PropertyValue",
      "propertyID": "thermalDestruction",
      "name": "Thermal Destruction",
      "description": "Thermal Destruction - material characteristics",
      "value": 616,
      "unitText": "K",
      "minValue": 228,
      "maxValue": 715
    },
    {
      "@type": "PropertyValue",
      "propertyID": "laserAbsorption",
      "name": "Laser Absorption",
      "description": "Laser Absorption - material characteristics",
      "value": 0.25,
      "unitText": "dimensionless",
      "minValue": 0.28,
      "maxValue": 126000
    },
    {
      "@type": "PropertyValue",
      "propertyID": "compressiveStrength",
      "name": "Compressive Strength",
      "description": "Compressive Strength - material characteristics",
      "value": 100,
      "unitText": "MPa",
      "minValue": 20,
      "maxValue": 200
    },
    {
      "@type": "PropertyValue",
      "propertyID": "fractureToughness",
      "name": "Fracture Toughness",
      "description": "Fracture Toughness - material characteristics",
      "value": 8,
      "unitText": "MPa m^{1/2}",
      "minValue": 0.7,
      "maxValue": 2.9
    },
    {
      "@type": "PropertyValue",
      "propertyID": "electricalResistivity",
      "name": "Electrical Resistivity",
      "description": "Electrical Resistivity - material characteristics",
      "value": 10000000000000000,
      "unitText": "Ω·m",
      "minValue": "9.5e+12",
      "maxValue": 100000000000000000
    },
    {
      "@type": "PropertyValue",
      "propertyID": "laserDamageThreshold",
      "name": "Laser Damage Threshold",
      "description": "Laser Damage Threshold - material characteristics",
      "value": 1.2,
      "unitText": "J/cm²",
      "minValue": 0.71,
      "maxValue": 2.6,
      "measurementTechnique": "scientific_literature"
    },
    {
      "@type": "PropertyValue",
      "propertyID": "ablationThreshold",
      "name": "Ablation Threshold",
      "description": "Ablation Threshold - material characteristics",
      "value": 0.58,
      "unitText": "J/cm²",
      "minValue": 0.39,
      "maxValue": 2.8,
      "measurementTechnique": "scientific_literature"
    },
    {
      "@type": "PropertyValue",
      "propertyID": "thermalDiffusivity",
      "name": "Thermal Diffusivity",
      "description": "Thermal Diffusivity - material characteristics",
      "value": "1.5e-07",
      "unitText": "m²/s",
      "minValue": 0,
      "maxValue": 0,
      "measurementTechnique": "scientific_literature"
    },
    {
      "@type": "PropertyValue",
      "propertyID": "thermalExpansion",
      "name": "Thermal Expansion",
      "description": "Thermal Expansion - material characteristics",
      "value": "4.7e-05",
      "unitText": "10^{-6} K^{-1}",
      "minValue": "5.9e-05",
      "maxValue": "0.0002",
      "measurementTechnique": "scientific_literature"
    },
    {
      "@type": "PropertyValue",
      "propertyID": "specificHeat",
      "name": "Specific Heat",
      "description": "Specific Heat - material characteristics",
      "value": 1170,
      "unitText": "J/(kg·K)",
      "minValue": 1,
      "maxValue": 2500,
      "measurementTechnique": "scientific_literature"
    },
    {
      "@type": "PropertyValue",
      "propertyID": "thermalConductivity",
      "name": "Thermal Conductivity",
      "description": "Thermal Conductivity - material characteristics",
      "value": 0.25,
      "unitText": "W/m·K",
      "minValue": 0.02,
      "maxValue": 3,
      "measurementTechnique": "scientific_literature"
    },
    {
      "@type": "PropertyValue",
      "propertyID": "laserReflectivity",
      "name": "Laser Reflectivity",
      "description": "Laser Reflectivity - material characteristics",
      "value": 0.06,
      "unitText": "",
      "minValue": 0.02,
      "maxValue": 0.05,
      "measurementTechnique": "scientific_literature"
    }
  ],
  "citation": "Z-Beam (2025). PEEK Laser Cleaning Dataset. Retrieved from https://www.z-beam.com/materials/plastic/thermoplastic/peek-laser-cleaning"
}