{
  "@context": "https://schema.org",
  "@type": "Article",
  "headline": "Hastelloy Laser Cleaning",
  "alternativeHeadline": "Advanced Laser Ablation Techniques for Hastelloy",
  "description": "Technical overview of Hastelloy laser cleaning applications and parameters",
  "keywords": [
    "surface treatment",
    "metal laser cleaning",
    "industrial laser",
    "hastelloy",
    "manufacturing laser cleaning",
    "laser ablation",
    "aerospace laser cleaning",
    "hastelloy laser cleaning",
    "chemical processing laser cleaning"
  ],
  "articleSection": "Materials Processing",
  "inLanguage": "en-US",
  "isAccessibleForFree": true,
  "author": {
    "@type": "Person",
    "name": "Yi-Chun Lin"
  },
  "about": {
    "@type": "Material",
    "name": "Hastelloy",
    "category": "metal",
    "density": 7.8,
    "description": "Hastelloy material for laser cleaning applications"
  },
  "mainEntity": {
    "@type": "HowTo",
    "name": "How to Laser Clean Hastelloy",
    "description": "Process for laser cleaning Hastelloy using 1064nm wavelength",
    "step": [
      {
        "@type": "HowToStep",
        "name": "Material Preparation",
        "text": "Secure Hastelloy component in laser processing fixture"
      },
      {
        "@type": "HowToStep",
        "name": "Parameter Configuration",
        "text": "Configure laser parameters: 1064nm wavelength"
      },
      {
        "@type": "HowToStep",
        "name": "Surface Treatment",
        "text": "Execute systematic scanning pattern for Hastelloy processing"
      }
    ]
  },
  "datePublished": "2025-09-20",
  "dateModified": "2025-09-20",
  "publisher": {
    "@type": "Organization",
    "name": "Z-Beam"
  }
}